wordkit/__init__.py
wordkit/_version.py
wordkit/corpora/__init__.py
wordkit/corpora/base/__init__.py
wordkit/corpora/base/reader.py
wordkit/corpora/base/utils.py
wordkit/corpora/corpora/__init__.py
wordkit/corpora/corpora/bpal.py
wordkit/corpora/corpora/celex.py
wordkit/corpora/corpora/cmudict.py
wordkit/corpora/corpora/lexiconproject.py
wordkit/corpora/corpora/lexique.py
wordkit/corpora/corpora/subtlex.py
wordkit/corpora/corpora/wordnet.py
wordkit/corpora/samplers/__init__.py
wordkit/corpora/samplers/samplers.py
wordkit/features/__init__.py
wordkit/features/base/__init__.py
wordkit/features/base/feature_extraction.py
wordkit/features/base/transformer.py
wordkit/features/holography/__init__.py
wordkit/features/holography/base.py
wordkit/features/holography/kanerva.py
wordkit/features/holography/permutation.py
wordkit/features/holography/plate.py
wordkit/features/orthography/__init__.py
wordkit/features/orthography/feature_extraction.py
wordkit/features/orthography/features.py
wordkit/features/orthography/linear.py
wordkit/features/orthography/ngram.py
wordkit/features/orthography/openngram.py
wordkit/features/phonology/__init__.py
wordkit/features/phonology/cv.py
wordkit/features/phonology/feature_extraction.py
wordkit/features/phonology/features.py
wordkit/features/phonology/grid.py
wordkit/features/phonology/onc.py
wordkit/features/semantics/__init__.py
wordkit/features/semantics/embedding.py
wordkit/features/semantics/wordnet.py
wordkit-4.3.3.dist-info/LICENSE
wordkit-4.3.3.dist-info/METADATA
wordkit-4.3.3.dist-info/WHEEL
wordkit-4.3.3.dist-info/top_level.txt
wordkit-4.3.3.dist-info/zip-safe
wordkit-4.3.3.dist-info/RECORD
