Metadata-Version: 2.1
Name: wordkit
Version: 4.3.3
Summary: Word featurization
Home-page: https://github.com/clips/wordkit
Author: Stéphan Tulkens
Author-email: stephan.tulkens@uantwerpen.be
License: GPLv3
Keywords: machine learning
Platform: UNKNOWN
Classifier: Intended Audience :: Developers
Classifier: Programming Language :: Python :: 3
Requires-Python: >=3
Requires-Dist: numpy
Requires-Dist: ipapy
Requires-Dist: pandas
Requires-Dist: scikit-learn
